dataflux_core/__init__.py
dataflux_core/download.py
dataflux_core/fast_list.py
dataflux_core/range_splitter.py
dataflux_core/user_agent.py
dataflux_pytorch/__init__.py
dataflux_pytorch/_helper.py
dataflux_pytorch/dataflux_checkpoint.py
dataflux_pytorch/dataflux_iterable_dataset.py
dataflux_pytorch/dataflux_mapstyle_dataset.py
dataflux_pytorch/lightning/__init__.py
dataflux_pytorch/lightning/dataflux_lightning_checkpoint.py
dataflux_pytorch/lightning/gcs_filesystem.py
dataflux_pytorch/lightning/path_utils.py
dataflux_pytorch/multipart_upload/__init__.py
dataflux_pytorch/multipart_upload/multipart.py
demo/image_segmentation/__init__.py
demo/image_segmentation/arguments.py
demo/image_segmentation/data_loader.py
demo/image_segmentation/pytorch_loader.py
demo/image_segmentation/submit.py
demo/image_segmentation/train.py
demo/image_segmentation/model/__init__.py
demo/image_segmentation/model/layers.py
demo/image_segmentation/model/losses.py
demo/image_segmentation/model/unet3d.py
demo/lightning/checkpoint/multinode/__init__.py
demo/lightning/checkpoint/multinode/strategies.py
demo/lightning/checkpoint/multinode/train.py
demo/lightning/text_based/__init__.py
demo/lightning/text_based/demo_model.py
gcs_torch_dataflux-1.4.0.dist-info/LICENSE
gcs_torch_dataflux-1.4.0.dist-info/METADATA
gcs_torch_dataflux-1.4.0.dist-info/WHEEL
gcs_torch_dataflux-1.4.0.dist-info/top_level.txt
gcs_torch_dataflux-1.4.0.dist-info/RECORD
