Metadata-Version: 2.1
Name: gcs-torch-dataflux
Version: 1.4.0
Summary: A GCS data loading integration for PyTorch
Maintainer-email: Google Dataflux Dev Team <dataflux-customer-support@google.com>
Project-URL: Homepage, https://github.com/GoogleCloudPlatform/dataflux-pytorch
Project-URL: Issues, https://github.com/GoogleCloudPlatform/dataflux-pytorch/issues
Classifier: Development Status :: 5 - Production/Stable
Classifier: Programming Language :: Python :: 3
Classifier: Programming Language :: Python :: 3.8
Classifier: Programming Language :: Python :: 3.9
Classifier: Programming Language :: Python :: 3.10
Classifier: Programming Language :: Python :: 3.11
Classifier: Programming Language :: Python :: 3.12
Classifier: License :: OSI Approved :: Apache Software License
Classifier: Operating System :: OS Independent
Classifier: Topic :: Utilities
Requires-Python: <3.13,>=3.8
License-File: LICENSE
Requires-Dist: torch>=2.0.1
Requires-Dist: numpy
Requires-Dist: google-cloud-storage
Requires-Dist: absl-py
Requires-Dist: lightning>=2.0
Provides-Extra: test
Requires-Dist: pytest; extra == "test"
